LICENSE
MANIFEST.in
README.md
setup.py
bellmanford/__init__.py
bellmanford/bellmanford.py
bellmanford.egg-info/PKG-INFO
bellmanford.egg-info/SOURCES.txt
bellmanford.egg-info/dependency_links.txt
bellmanford.egg-info/requires.txt
bellmanford.egg-info/top_level.txt