Metadata-Version: 1.0
Name: bellmanford
Version: 0.2.1
Summary: 
Home-page: https://github.com/nelsonuhan/bellmanford
Author: Nelson Uhan
Author-email: nelson@uhan.me
License: BSD
Platform: UNKNOWN
